KartRider/__init__.py
KartRider/apiwrapper.py
KartRider/basedata.py
KartRider/match.py
KartRider/metadata.py
KartRider/user.py
KartRider/utils.py
KartRider-0.6.0.dist-info/LICENSE
KartRider-0.6.0.dist-info/METADATA
KartRider-0.6.0.dist-info/WHEEL
KartRider-0.6.0.dist-info/top_level.txt
KartRider-0.6.0.dist-info/RECORD
