Metadata-Version: 2.1
Name: KartRider
Version: 0.6.0
Summary: KartRider Open API Python wrapper
Home-page: https://github.com/laoraid/KartRider.py
Author: Laoraid
Author-email: a99azaz@gmail.com
License: MIT
Keywords: KartRider
Platform: UNKNOWN
Classifier: Development Status :: 4 - Beta
Classifier: Intended Audience :: Developers
Classifier: Programming Language :: Python :: 3.6
Classifier: Programming Language :: Python :: 3.7
Classifier: License :: OSI Approved :: MIT License
Classifier: Natural Language :: Korean
Classifier: Topic :: Software Development :: Libraries :: Python Modules
Requires-Python: >=3.6
Requires-Dist: requests
